setup.py
aiojsonflow/__init__.py
aiojsonflow/engine.py
aiojsonflow/exceptions.py
aiojsonflow.egg-info/PKG-INFO
aiojsonflow.egg-info/SOURCES.txt
aiojsonflow.egg-info/dependency_links.txt
aiojsonflow.egg-info/top_level.txt
aiojsonflow/lib/__init__.py
aiojsonflow/lib/math.py